<?xml version="1.0" encoding="utf-8" ?>
<dwsync>
<file name="bg_patent_new.jpg" server="simyoonji.dothome.co.kr" local="133232127600000000" remote="133232127600000000" Dst="0" />
<file name="ico_patent_situation01.png" server="simyoonji.dothome.co.kr" local="133232127600000000" remote="133232127600000000" Dst="0" />
<file name="ico_patent_situation02.png" server="simyoonji.dothome.co.kr" local="133232127600000000" remote="133232127600000000" Dst="0" />
<file name="ico_patent_situation03.png" server="simyoonji.dothome.co.kr" local="133232127600000000" remote="133232127600000000" Dst="0" />
<file name="ico_patent_situation04.png" server="simyoonji.dothome.co.kr" local="133232127600000000" remote="133232127600000000" Dst="0" />
<file name="ico_patent_situation05.png" server="simyoonji.dothome.co.kr" local="133232127600000000" remote="133232127600000000" Dst="0" />
<file name="ico_patent_situation06.png" server="simyoonji.dothome.co.kr" local="133232127600000000" remote="133232127600000000" Dst="0" />
<file name="img_subbaner_business.jpg" server="simyoonji.dothome.co.kr" local="133232127600000000" remote="133232127600000000" Dst="0" />
<file name="bg_patent_intellectual.jpg" server="simyoonji.dothome.co.kr" local="133232918400000000" remote="133232918400000000" Dst="0" />
<file name="bg_patents_list_type1.png" server="simyoonji.dothome.co.kr" local="133232944800000000" remote="133232944800000000" Dst="0" />
<file name="bg_patents_list_type2.png" server="simyoonji.dothome.co.kr" local="133232944800000000" remote="133232944800000000" Dst="0" />
<file name="btn_paging_first.png" server="simyoonji.dothome.co.kr" local="133233037200000000" remote="133233037200000000" Dst="0" />
<file name="btn_paging_last.png" server="simyoonji.dothome.co.kr" local="133233037200000000" remote="133233037200000000" Dst="0" />
<file name="btn_paging_next.png" server="simyoonji.dothome.co.kr" local="133233037200000000" remote="133233037200000000" Dst="0" />
<file name="btn_paging_prev.png" server="simyoonji.dothome.co.kr" local="133233037200000000" remote="133233037200000000" Dst="0" />
<file name="btn_topsearch.png" server="simyoonji.dothome.co.kr" local="133233073800000000" remote="133233073800000000" Dst="0" />
<file name="img_subbaner_company.jpg" server="simyoonji.dothome.co.kr" local="133233037200000000" remote="133233037200000000" Dst="0" />
<file name="news1-1.jpg" server="simyoonji.dothome.co.kr" local="133233037200000000" remote="133233037200000000" Dst="0" />
<file name="news1-2.jpg" server="simyoonji.dothome.co.kr" local="133233037200000000" remote="133233037200000000" Dst="0" />
<file name="news1-3.jpg" server="simyoonji.dothome.co.kr" local="133233037200000000" remote="133233037200000000" Dst="0" />
<file name="news1-4.jpg" server="simyoonji.dothome.co.kr" local="133233037200000000" remote="133233037200000000" Dst="0" />
<file name="news1-5.jpg" server="simyoonji.dothome.co.kr" local="133233037200000000" remote="133233037200000000" Dst="0" />
</dwsync>